iftns/__init__.py
iftns-1.0.0.dist-info/METADATA
iftns-1.0.0.dist-info/WHEEL
iftns-1.0.0.dist-info/top_level.txt
iftns-1.0.0.dist-info/RECORD
