Metadata-Version: 2.1
Name: iftns
Version: 1.0.0
Author: Margret Westerkamp
Author-email: margret@mpa-garching.mpg.de
